telegram_bell/__init__.py
telegram_bell/bell.py
telegram_bell/config.py
telegram_bell/exceptions.py
telegram_bell/notifier.py
telegram_bell/session.session
telegram_bell-0.7.1.dist-info/entry_points.txt
telegram_bell-0.7.1.dist-info/WHEEL
telegram_bell-0.7.1.dist-info/METADATA
telegram_bell-0.7.1.dist-info/RECORD
